{
	"configurations" : 
	[
		{
			"directories" : 
			[
				{
					"build" : ".",
					"jsonFile" : "directory-.-Debug-d0094a50bb2071803777.json",
					"minimumCMakeVersion" : 
					{
						"string" : "3.8"
					},
					"projectIndex" : 0,
					"source" : ".",
					"targetIndexes" : 
					[
						0
					]
				}
			],
			"name" : "Debug",
			"projects" : 
			[
				{
					"directoryIndexes" : 
					[
						0
					],
					"name" : "task-tracker",
					"targetIndexes" : 
					[
						0
					]
				}
			],
			"targets" : 
			[
				{
					"directoryIndex" : 0,
					"id" : "task-tracker::@6890427a1f51a3e7e1df",
					"jsonFile" : "target-task-tracker-Debug-2a6b9e4763ab56a6ed01.json",
					"name" : "task-tracker",
					"projectIndex" : 0
				}
			]
		}
	],
	"kind" : "codemodel",
	"paths" : 
	{
		"build" : "D:/cpp/projects/task-tracker/out/build/x64-debug",
		"source" : "D:/cpp/projects/task-tracker"
	},
	"version" : 
	{
		"major" : 2,
		"minor" : 7
	}
}
